dicta/__init__.py
dicta/dicta.py
dicta-1.2.3.dist-info/METADATA
dicta-1.2.3.dist-info/WHEEL
dicta-1.2.3.dist-info/licenses/LICENSE
dicta-1.2.3.dist-info/RECORD
