Metadata-Version: 2.4
Name: dicta
Version: 1.2.3
Summary: A 'dict' subclass that detects changes in its data structure. It triggers a callback and/or exports its data to a JSON file if the data has changed.
Project-URL: Homepage, https://github.com/mextex/dicta
Author-email: Peter Wendl <dev@peterwendl.de>
License: MIT License
License-File: LICENSE
Keywords: callback,dict,fileimport,json,listener,nested-objects,serialization
Classifier: License :: OSI Approved :: MIT License
Classifier: Operating System :: OS Independent
Classifier: Programming Language :: Python :: 3
Requires-Python: >=3.8
